<mediawiki xmlns="http://www.mediawiki.org/xml/export-0.10/" xmlns:xsi="http://www.w3.org/2001/XMLSchema-instance" xsi:schemaLocation="http://www.mediawiki.org/xml/export-0.10/ http://www.mediawiki.org/xml/export-0.10.xsd" version="0.10" xml:lang="zh">
  <siteinfo>
    <sitename>Wikipedia</sitename>
    <dbname>zhwiki</dbname>
    <base>https://zh.wikipedia.org/wiki/Wikipedia:%E9%A6%96%E9%A1%B5</base>
    <generator>MediaWiki 1.29.0-wmf.21</generator>
    <case>first-letter</case>
    <namespaces>
      <namespace key="-2" case="first-letter">Media</namespace>
      <namespace key="-1" case="first-letter">Special</namespace>
      <namespace key="0" case="first-letter" />
      <namespace key="1" case="first-letter">Talk</namespace>
      <namespace key="2" case="first-letter">User</namespace>
      <namespace key="3" case="first-letter">User talk</namespace>
      <namespace key="4" case="first-letter">Wikipedia</namespace>
      <namespace key="5" case="first-letter">Wikipedia talk</namespace>
      <namespace key="6" case="first-letter">File</namespace>
      <namespace key="7" case="first-letter">File talk</namespace>
      <namespace key="8" case="first-letter">MediaWiki</namespace>
      <namespace key="9" case="first-letter">MediaWiki talk</namespace>
      <namespace key="10" case="first-letter">Template</namespace>
      <namespace key="11" case="first-letter">Template talk</namespace>
      <namespace key="12" case="first-letter">Help</namespace>
      <namespace key="13" case="first-letter">Help talk</namespace>
      <namespace key="14" case="first-letter">Category</namespace>
      <namespace key="15" case="first-letter">Category talk</namespace>
      <namespace key="100" case="first-letter">Portal</namespace>
      <namespace key="101" case="first-letter">Portal talk</namespace>
      <namespace key="118" case="first-letter">Draft</namespace>
      <namespace key="119" case="first-letter">Draft talk</namespace>
      <namespace key="828" case="first-letter">模块</namespace>
      <namespace key="829" case="first-letter">模块讨论</namespace>
      <namespace key="2300" case="first-letter">Gadget</namespace>
      <namespace key="2301" case="first-letter">Gadget talk</namespace>
      <namespace key="2302" case="case-sensitive">Gadget definition</namespace>
      <namespace key="2303" case="case-sensitive">Gadget definition talk</namespace>
      <namespace key="2600" case="first-letter">Topic</namespace>
    </namespaces>
  </siteinfo>
  <page>
    <title>鐵路列車</title>
    <ns>0</ns>
    <id>24581</id>
    <revision>
      <id>44196599</id>
      <parentid>44196185</parentid>
      <timestamp>2017-05-01T06:43:38Z</timestamp>
      <contributor>
        <username>Wolfch</username>
        <id>83117</id>
      </contributor>
      <minor/>
      <comment>取消[[Special:Contributions/Messi neymar jr|Messi neymar jr]]（[[User talk:Messi neymar jr|对话]]）的编辑；更改回[[Special:Contributions/Raymon090|Raymon090]]的最后一个版本</comment>
      <model>wikitext</model>
      <format>text/x-wiki</format>
      <text xml:space="preserve" bytes="19208">{{Portal|鐵路}}
{{refimprove|time=2013-04-14T02:41:38+00:00}}
{{noteTA
|0=zh-hans:动力分散式; zh-hant:動力分散式;
|1=zh-hans:车厢;zh-hk:車卡;zh-tw:車廂;
|2=zh-hans:无动力车卡;zh-hk:拖卡;zh-tw:無動力車卡;
|3=zh-hans:分散式; zh-hant:分散式;
|4=zh-tw:線路;zh-cn:线路;zh-hk:綫路;
}}
{{Redirect|火車}}
[[File:MTR-EastRailLineTrain.jpg|thumb|250px|由[[電力]]驅動的雙軌列車]]
[[File:4-6-0 Odney Manor 7828 at Watchet (21912938946).jpg|thumb|250px|由[[煤]]驅動的[[蒸氣火車]]]]
'''鐵路列車'''，简称'''列車'''，俗稱'''火車'''，是指在[[鐵路軌道]]上行駛的[[载具|車輛]]，通常由多節[[鐵路車輛|車廂]]所組成，可以載運[[乘客]]或是[[商品|貨物]]。

根据《[[中华人民共和国铁路技术管理规程]]》的定义，[[列车]]是“指编成的车列并挂有机车及规定的列车标志。单机、自轮运转特种设备，虽未完全具备列车条件，亦应按列车办理。”&lt;ref&gt;{{cite book|title=铁路技术管理规程}}&lt;/ref&gt;

火車的動力來源可以來自個別的[[鐵路機車]]或是將動力分散到每個車廂的[[動力分散式列車]]。19世紀早期的火車的鐵路機車以[[蒸汽機車]]為主，1910年代起開始更換為[[柴油機車]]，較不耗人力，也比較乾淨，但較複雜及昂貴，後來也逐漸換成[[電力機車]]（電力由[[接触网供电|高架電纜]]或[[軌道供電|第三軌]]提供），客車也開始採用[[動力分散式列車]]。其他的動力來源包括馬、纜線、重力、[[氣動]]、電池或是[[燃氣渦輪發動機]]。火車軌道一般會由二條、三條或是四條[[鐵軌]]組成，不過也有[[單軌鐵路]]及不需要軌道的[[磁懸浮列車]]。火車一詞英文 train 的字根是來自[[古法語]]的 ''trahiner'' ，此詞是來自[[拉丁文]]的 ''trahere'' ，意思是「拉」&lt;ref&gt;{{cite web | title = Train (noun) | work = (definition – Compact OED) | publisher = Oxford University Press | url = http://www.askoxford.com/concise_oed/train?view=uk | accessdate = 2008-03-18}}&lt;/ref&gt;。

火車包括一個或多個[[鐵路機車]]及載人或載貨的[[鐵路車輛]]，也有可能是每個車廂都有動力的[[動力分散式列車]]。有許多種針對不同用途設計的火車，除一般火車外，還有{{link-en|大气鐵路|Atmospheric railway}}、[[單軌鐵路]]、[[高速鐵路]]、[[磁懸浮列車]]、[[膠輪路軌系統]]、[[纜索鐵路]]、[[齒軌鐵路]]等。

客車是指載運乘客的火車，一般長度較長，速度也較快。其中[[高速鐵路]]是以速度快及長距離著名，為了讓時速超過{{convert|500|km/h|mph|abbr=on}}，近年來已在研究[[磁懸浮列車]]，到2015年時，中國的[[上海磁浮示範運營線]]和日本的[[東部丘陵線]]是仍在商業運營的兩條磁懸浮列車。

在英國等國家，[[有軌電車]]和火車的差異很明確，而且在法律中有明確規定。有些現代的有軌電車會用「[[輕軌運輸]]」這個名稱，不過[[輕軌運輸]]也可能是指介於有軌電車和火車之間的運輸方式，類似[[捷運]]，可是有捷運中沒有的[[平交道]]。

== 發展 ==
[[File:Tzarskoselskaya Railway - Watercolour.jpg|thumb|250px|俄罗斯原始的铁路运输系统。]]
[[File:Pioneer Zephyr meal service 1934.jpg|thumb|250px|1930年代英國鐵路餐車。]]

1807年，英國威爾斯出現第一個鐵路列車。&lt;ref&gt;《Discovery Channel Magazine探索頻道雜誌》，第1刊，6頁，ISSN：2306-5486&lt;/ref&gt;

1831年8月9日，德威特·克林頓·普爾德駕駛著火車行駛在[[紐約]]的[[奧爾巴尼]]客運鐵路線。1840年代，開始使用[[機械手臂|機械臂]]板號機。1857年，人們開始使用比鍛鐵[[鐵軌]]更堅固的鋼軌。1863年，[[英国]][[伦敦]]建成第一條[[地下鐵路]]&lt;ref&gt;{{cite book|title=科學月刊|url=http://books.google.com/books?id=lfgdAQAAMAAJ|date=January 1992|publisher=科學月刊雜誌社}}&lt;/ref&gt;，也就是[[大都會鐵路]]。

1864年，喬治‧M‧普爾曼設計出一種新型的臥鋪車。1879年，世界最早的電力火車開始運行。1931年，第一條從東到西橫越[[非洲大陸]]的[[本格拉]]－加丹加鐵路在南部[[非洲]]建成通車。

== 動力 ==
{{main|鐵路機車}}

最初的列車是由繩索、重力或馬匹&lt;ref name=&quot;顏進儒2006&quot;&gt;{{cite book|author=顏進儒|title=運輸學|url=http://books.google.com/books?id=ACFqwCAqMm4C&amp;pg=PA149|year=2006|publisher=五南圖書出版股份有限公司|isbn=978-957-11-4246-3|pages=149–}}&lt;/ref&gt;拉動的。到了十九世紀，多數的列車都改由[[蒸汽機車]]牽引。1940年代以後蒸汽機車漸由較清潔及需要較少勞力的[[柴油機車]]取代，後來又出現[[電力機車]]以及動力分散在各個車廂的[[動力分散式列車]]。1970年為止，大部份國家日常使用鐵路機車至少都已{{link-en|內燃化|dieselisation}}或是採用更新的技術，當時只有一些煤和人工便宜的地方仍使用蒸汽機車，例如[[中國]]最後運營的大型蒸汽機車是於2005年12月9日在內蒙古退役&lt;ref&gt;[http://scitech.people.com.cn/BIG5/3931715.html 最后一批蒸汽機車退役]&lt;/ref&gt;。不過許多國家的观光铁路仍使用蒸汽機車，只是針對休闲觀光或是[[鐵道迷]]的市場。

[[電氣化鐵路]]的最初投資很大，但按每里計算則是運作成本最低的。因此只有高流量的線路才適合電氣化。電氣化列車可能使用[[高架電纜]]或[[軌道供電|第三軌]]取電。

最近已在進行電力機車使用[[燃料電池]]驅動的研究&lt;ref&gt;{{cite web|url=http://www.hydrogencarsnow.com/blog2/index.php/hydrogen-vehicles/i-hear-the-hydrogen-train-a-comin-its-rolling-round-the-bend/ |title=Hydrogen trains |publisher=Hydrogencarsnow.com |date= |accessdate=2014-05-18}}&lt;/ref&gt;&lt;ref&gt;{{cite web|url=http://www.bnsf.com/media/news/articles/2008/01/2008-01-09a.html |title=Vehicle Projects Inc. Fuel cell locomotive |publisher=Bnsf.com |date= |accessdate=2014-05-18}}&lt;/ref&gt;。燃料電池電力機車結合了非電力機車不需要供電系統以及電力機車零排放的優點。不過至2014年為止，{{link-en|燃料車輛|Fuel cell vehicle}}的初期成本仍非常高。

以動力的單位千瓦特（KW）除以能夠牽引的重量公噸（Ton）來計算動力機車頭的效能稱為牽引能力比，[[蒸汽機車]]效能最低，其次是[[柴油機車]]（電力傳動比液力傳動效益高），[[電力機車]]或是[[電聯車]]相對而言就經濟的多。因為不需消耗額外的動能來牽引產生動力的引擎。

牽引動能比由小排到大依序為：（客运飞機、摩托車、一般家庭的汽車、公路上跑的卡車、農用牽引機、全挂拖車、）蒸氣機車、柴油液力传動機車、柴油電力传动機車、電力機車、柴油动車租、高鐵动車组、電力动車组（、客輪、漁船、油輪）。

若考慮單位燃料或是單位動力的成本來營運軌道車輛，是以小編組來做區間運轉有最佳能量使用經濟效益，{{fact|也就是4車一編組。每站都停的[[區域鐵路|通勤電聯車]]最具效益。}}更具能量和時間效益的是不停站電車，乘客登車後均直接坐到目的站才停下來，可以一車一編組按需求調度去不同的目的地。

== 種類 ==
按不同条件区分，火车可以有多个分类，主要的分類是載客列車及貨運列車，以下是一些其他的分類。

=== 路轨 ===
按路軌分類，列車可分為[[鐵路軌道|鐵軌]]、[[單軌鐵路|單軌]]、[[磁懸浮列車|磁浮]]。亦有[[登山鐵路]]特別使用的[[齒軌鐵路]]、及由纜索拉動的[[索道，亦有使用自走的[[動車組]]。

某些列車由多過一個的機車牽引。在[[北美洲]]，貨車經常是由三、四個以至五個機車[[機車重聯|重聯]]牽引。另外也有把機車置於列車頭尾及中間位置牽引，如[[大秦铁路|大秦鐵路]]。

也有列車是專門為軌道維修而設的。

===區間列車===
[[File:Aikan-shuttle.JPG|thumb|250px|日本[[爱知环状铁道线]]的區間列車]]
區間列車指的是在只在兩點間來回的鐵路列車，一般提供的是頻繁的短程列車服務。但在臺灣，區間指的是區域通勤。&lt;ref&gt;{{cite web|title=Shuttle|url=http://www.collinsdictionary.com/dictionary/english/shuttle?showCookiePolicy=true|work=[http://www.collinsdictionary.com/dictionary/english/ Collins English Dictionary]|publisher=Collins|accessdate=6 February 2013}}&lt;/ref&gt;&lt;ref&gt;{{cite web|title=shuttle train|url=http://www.merriam-webster.com/dictionary/shuttle%20train|work=[http://www.merriam-webster.com/dictionary/ Merriam-Webster Dictionary]|publisher=Merriam-Webster, Incorporated|accessdate=6 February 2013}}&lt;/ref&gt;  世界上很多國家的鐵路都有區間列車。&lt;ref&gt;{{cite web|title=Glossar Öffentlicher Verkehr|url=http://www.ivt.ethz.ch/oev/glossar/#S|work=[http://www.ivt.ethz.ch/index_EN Institute for Transport Planning and Systems website]|publisher=[[ETH Zurich]]|accessdate=6 February 2013}} {{de icon}}&lt;/ref&gt;

== 載客列車 ==
[[File:DSBtrain.jpg|thumb|250px|機車牽引的客車]]
[[File:E5 Series Shinkansen and the X-shaped Bridge viewed from AER.JPG|250px|thumb|right|日本新幹線於[[仙台站]]的[[新幹線E5系電力動車組|E5系]]。]]
載客的列車用[[鐵路車輛#客車|客車廂]]，把乘客從[[鐵路車站|車站]]運送列另一車站。車站間的距離可能不足一公里，亦有可能長達數百公里。載客列車可以是本身有動力的[[動力分散式列車]]，也可以是[[鐵路機車]]配合無動力的[[鐵路客車]]。乘客會在[[鐵路車站|火車站]]上下車，一般而言載客列車有固定的[[公共交通时刻表]]，[[货物列车]]需要禮讓載客列車先行。

載客列車會有[[列車長]]監督列車的正常運行，列車長也會和其他列車的工作人員合作，例如服务员或是搬运工。在北美火車客運的鼎盛时期，列車上會有兩個列車長，其中一個負責[[卧铺车]]的人員。

===高速鐵路===
{{main|高速鐵路}}
高速鐵路是一种营运速度比较普通铁路高的鐵路運輸系統。截至2013年，世界上主要运行的高铁系統的最高營運时速大约都設定在300公里（包括[[德国]]、[[日本]]、[[台灣]]、[[意大利]]、[[英国]]和[[大韩民国|韓国]]的系統），少部分系統擁有比較高的時速。

第一個正式營運的高速鐵路是日本的[[新幹線]]，在於1964年10月1日[[1964年夏季奧林匹克運動會|東京奧運]]前夕開始通車營運。

若是距離不超過{{convert|500|to|600|km|mi|0|abbr=on}}，多半高速鐵路在時間及價格上都比飛機划算，因為[[機場]]的{{link-en|報到|check-in}}及登機大約共需二個小時&lt;ref&gt;{{cite book| author=Central Japan Railway| title=Central Japan Railway Data Book 2006| year=2006| pages=16 }}&lt;/ref&gt;。而且若考慮飛機[[起飛]]時的耗油，火車單位距離的運營成本也比較航空要低。不過當距離變長，起飛耗油與高空飛行使佔總成本的比例降低，加上節省下來的時間，空運就比較有競爭力了。
[[File:台灣高鐵-一般列車停靠於桃園站南下月台.JPG|缩略图|台灣高鐵]]
部份高速列車的車身可以擺動，稱為[[擺式列車]]，以便在轉彎時無需降低車速。例如[[潘多利諾]]的電聯車及[[新幹線N700系電聯車]]等。

長途客車有時會有[[卧铺车|卧車]]，但一般的[[高速鐵路]]很少有卧車，因為它們一般在入黑以前便會到抵達目的地。

高速列车的车体大量的采用了复合材料。由复合材料做成的构件重量轻、强度高、刚性大，不仅大大减轻了车厢重量、降低噪声、振动，还提高安全性、舒适性，增加了列车的寿命并降低了维修成本&lt;ref&gt;蒋鞠慧，陈敬菊. 复合材料在轨道交通上的应用与发展. 玻璃钢/复合材料. 2009，第6期. 81~85.&lt;/ref&gt;。在轨道佳通内部设施与装饰材料方面，常采用[[复合材料]]、[[夹芯结构材料|夹层结构材料]]、[[PET泡沫芯材|PET泡沫夹层结构]]、[[芯材|巴沙轻木]]等，而作为车辆的承重结构，车体如今也已开始采用诸如[[碳纤维]]（CF）、[[玻璃纖維強化塑膠|玻璃纤维]]（fiberglass）、[[环氧树脂]]（Epoxy resin）和[[酚醛树脂]]（PF）等复合材料，而用蜂窝、夹层泡沫结构也比传统的铝结构质量减轻了30%。这都为高速列车的性能提升奠定了基础。

===磁浮列車===
{{main|磁浮列車}}

[[磁懸浮列車|磁浮鐵路]]是鐵路列車中較先進的新發明，是為了讓時速超過{{convert|500|km/h|mph|abbr=on}}而開始的研究。世界上首條商業運營的磁浮列車線路是英國{{link-en|伯明罕磁浮|AirRail_Link}}。到2014年時，中國的[[上海磁浮示範運營線]]和日本的[[東部丘陵線]]是仍在商業運營的兩條磁懸浮列車，上海磁浮示範運營線的速度最快，約有{{convert|430|km/h|mph|abbr=on}}。

===長程列车===
長程列车會經過數個城市，或一國家的幾個區域，有時甚至會經過數個國家，一般會附帶[[进餐车厢|餐車]]方便乘客在路途中用餐，若是過夜的車次也會有[[卧車]]。若距離超過五百英哩以上的旅程多半會選擇搭飛機，但長程列车也是一個受歡迎的選擇，而且也可能是少數較便宜的選擇。

===城际列车===
{{main|城际列车}}
[[File:TRA E1001 in Hualien Station 20070123.jpg|缩略图|台灣城際列車-E1000 ]]
城际列车是連結城市間的鐵路運輸服務。可以提供旅客商務旅行、觀光等多方面的服務。

城際列車和及其他軌道運輸最大的不同點在於：&lt;ref name=&quot;建構臺灣都會區域整合性通勤鐵路之芻議&quot;&gt;{{cite web | url=http://www.cepd.gov.tw/dn.aspx?uid=7916 | title=建構臺灣都會區域整合性通勤鐵路之芻議 | accessdate=2013-02-13}}&lt;/ref&gt;

*運輸距離較長（距離通常會超過200公里）
*停靠站數較少
*營運速度較快
*列車內裝較豪華，跨夜行駛的列車甚至會連結[[卧铺车|臥舖車]]

===短程列车===
城市之間不停沿途小站的市際列車稱為'''快車'''或'''特快'''。各小站都停的稱為'''普通客車'''、'''普客'''或'''區間車'''。

===市區內列车===
有些大城市有短距離的[[通勤铁路|通勤列車]]往來市郊住宅區及市中心。這些通勤列車經常亦是[[城市軌道交通系統]]的一部分。很多的通勤車都是以站立為主，座位較少。有些地區會用雙層客車來增加載客。而高速列車及卧車亦有是雙層的。

城市軌道交通系有時被稱作地下鐵路，但它們在市中心以外可能會在路面或架空路軌上行走。這類列車的加速及減速一般都比長途車快，通常亦有更多的車門以供乘客上落。

[[有軌電車|路面電車]]或[[輕便鐵路]]一般最多只會有兩個車廂一同行走。路面電車通常會與其他車在同一條馬路上行駛。輕便鐵路是對很多現代化路面電車的稱謂，因為它們介乎[[有軌電車|路面電車]]及[[重型鐵路系統|重鐵]]（即一般鐵路列車）之間。路面電車跟輕便鐵路其實沒有很明確的分野，很多時分類都是約定俗成。

[[單軌鐵路]]是鐵路列車中較先進的新發明，不過應用仍然很少。

[[地鐵|地下鐵路]]、[[輕軌運輸系統|輕便鐵路]]、通勤列車有時會被統稱為'''快速運輸系統'''。

== 貨運列車 ==
貨運列車拖動的是[[鐵路車輛#貨車|貨車載貨車廂]]。
[[File:BNSF 7663.jpg|thumb|250px|貨運列車]]

世上鐵路運輸使用得最多的是鐵路貨運。[[美国]]的鐵路主要是用作貨運。

在合適的情況下，鐵路貨運比道路貨運便宜很多，亦更節省能源。鐵路貨運最適合用來長途運載大量的貨物。但對於短途或小量的貨物則較為不適合。鐵路貨運的最大缺點是缺乏彈性。在不少國家鐵路貨運正漸被以道路貨運取代。但亦有很多政府因為環境的考慮，而設法鼓勵使用鐵路。

鐵路使用的載貨車廂有多種，現代最常見的是[[貨櫃]]（[[集裝箱]]）車。它們可以由起重機吊起，從車廂運到船或貨車上。
有些國家的貨櫃車廂採用附帶方式，又稱為「{{link-en|背載式運輸|Piggy-back (transportation)}}」，[[载货汽车|貨櫃車]]可以把貨櫃連拖架駛上列車車廂上。到達目的地後直接由貨櫃車頭把貨櫃開走。[[英国]]、[[法国]]之間的[[英法海峽隧道]]鐵路線便是採用這種設計。

其他的貨車車廂包括有：運送車輛的平車、散裝貨物的敞車、冷凍食物的冷藏車、運送豬或牛等動物的棚車、運送煤炭壙物穀類的漏斗車、運送汽油等液體的罐車及運送闊大貨物的大物車等等。

==轉向架==
[[Image:Railroad truck,FM55-20.Fig8-8.png|thumb|美規的鐵路轉向架及[[軸套]]]]
{{Main|轉向架}}
在[[機械]]術語中，[[轉向架]]（bogie，{{IPAc-en|ˈ|b|oʊ|ɡ|i}} {{Respell|BOH|ghee}})）是一個連接在車廂上，有[[輪子]]的[[底盘]]或框架。轉向架可以在車子下方固定的位置，像貨運卡車一様，也可以用[[連接式設計]]，轉向架在兩個車廂之間，或像[[履帶]]車輛一様放在懸吊系統。一般一個車廂或鐵路機車會有兩個轉向架，一頭一個。另一個作法會將轉向架放在兩個車廂之間。大部份的轉向架有兩個輪軸，這也是最簡單的設計，不過有些設計乘載重載的轉向架最多會到五個輪軸。重載的車廂可能會有兩個以上的轉向架，利用跨度垫（span bolster）平衡負載，並連接轉向架和車廂。通常列車的車廂地板會比轉向架高，不過車廂的地板也可以比轉向架低，例如雙層列車，在符合高度限制的條件下增加車內的空間，或是一些沒有階段的低地板火車。

== 相册 ==
&lt;gallery caption=&quot;鐵路列車&quot; widths=&quot;180px&quot; heights=&quot;120px&quot; perrow=&quot;3&quot;&gt;
File:ID_diesel_loco_CC_201-05_060327_4217_kta.jpg|编号#CC201-05的GE U20C火车头。
File:Diesel_locomotive.JPG|编号#CC203-22的GE U20C &quot;Full-Width Cabin&quot;火车头。
File:ID_diesel_loco_CC_204-06_060403_2512_mri.jpg|全电脑化的GE U20C火车头，编号为#CC204-06。
File:Dentetsu toyama sta06st3200.jpg|日本[[富山車站_(日本)|富山車站]]火車駕駛通行證{{link-ja|佈告欄|掲示板}}
[...]
&lt;/gallery&gt;

== 火车的动画 ==
&lt;gallery&gt;
File:Deviatkino-Ruchi ER2.ogv
File:ER2-973 Ligovo.ogg
File:Otloczyn miejsce katastrofy.ogv
&lt;/gallery&gt;

== 相關 ==
{{Portal|鐵路|P train.svg}}
*[[鐵路事故列表]]
*[[混合動力鐵路車輛]]
*[[單軌鐵路]]
*[[鐵路運輸]]
*[[裝甲列車]]
*[[鐵道模型]]
*[[動車組]]
*[[动拖比]]
*[[:Category:铁路模拟游戏]]

== 参考文献 ==
{{Reflist|30em}}

== 外部链接 ==
* {{Commons-inline|Train}}

{{-}}
{{鐵路}}

[[Category:鐵路列車| ]]</text>
      <sha1>qhvzxnexwsb94ki1oxm0va2949iytcv</sha1>
    </revision>
  </page>
</mediawiki>
